{
  "schemaVersion": 1,
  "id": "01KCGP9ZG1KPX3AECN0BFP1YGY",
  "slug": "new_test_league",
  "name": "new test league",
  "season": 1,
  "status": "active",
  "settings": {
    "pointsWin": 3,
    "pointsDraw": 1,
    "pointsLoss": 0,
    "maxTeams": 16,
    "lockTeams": false
  },
  "teams": [
    {
      "id": "01KCGPACYZY3NBCA4ZFNBXBPTK",
      "name": "Amazons",
      "race": "Amazon",
      "coachName": "Coach 1",
      "colors": {
        "primary": "#1e8a00",
        "secondary": "#c5a059"
      }
    },
    {
      "id": "01KCGPBJR94R81D2REP21EZ48N",
      "name": "Norse",
      "race": "Norse",
      "coachName": "coach 2",
      "colors": {
        "primary": "#1e00ff",
        "secondary": "#c7c7c7"
      }
    },
    {
      "id": "01KCX7NVFQFM37NSQSS1YRAG4W",
      "name": "Khorne",
      "race": "Khorne",
      "coachName": "",
      "colors": {
        "primary": "#222222",
        "secondary": "#c5a059"
      }
    },
    {
      "id": "01KCX7Q13ZRTN03209NG4YSK4B",
      "name": "Nurgle",
      "race": "Nurgle",
      "coachName": "Coach 4",
      "colors": {
        "primary": "#8c009e",
        "secondary": "#424242"
      }
    }
  ],
  "matches": [
    {
      "id": "01KCGPDNC73K6KAAJN632HD31T",
      "season": 1,
      "round": 1,
      "homeTeamId": "01KCGPACYZY3NBCA4ZFNBXBPTK",
      "awayTeamId": "01KCGPBJR94R81D2REP21EZ48N",
      "status": "completed",
      "date": "2025-12-15",
      "score": {
        "home": 0,
        "away": 3
      },
      "casualties": {
        "homeInflicted": 0,
        "awayInflicted": 1
      },
      "hasReport": true,
      "reportId": "01KCGPDNC73K6KAAJN632HD31T"
    },
    {
      "id": "01KCGPDW3NR2HSZNNZ1BVE11N0",
      "season": 1,
      "round": 2,
      "homeTeamId": "01KCGPBJR94R81D2REP21EZ48N",
      "awayTeamId": "01KCGPACYZY3NBCA4ZFNBXBPTK",
      "status": "completed",
      "date": "2025-12-15",
      "score": {
        "home": 1,
        "away": 2
      },
      "casualties": {
        "homeInflicted": 1,
        "awayInflicted": 0
      },
      "hasReport": true,
      "reportId": "01KCGPDW3NR2HSZNNZ1BVE11N0"
    },
    {
      "id": "01KCGT7TAP6E4YMTGHW5DQ2RN6",
      "season": 1,
      "round": 3,
      "homeTeamId": "01KCGPACYZY3NBCA4ZFNBXBPTK",
      "awayTeamId": "01KCGPBJR94R81D2REP21EZ48N",
      "status": "completed",
      "date": "2025-12-15",
      "score": {
        "home": 2,
        "away": 1
      },
      "casualties": {
        "homeInflicted": 0,
        "awayInflicted": 0
      },
      "hasReport": true,
      "reportId": "01KCGT7TAP6E4YMTGHW5DQ2RN6"
    }
  ]
}